{
  "utrecht": {
    "form-field-error-message": {
      "icon": {
        "size": {
          "$type": "sizing",
          "$value": "{nijmegen.icon.functional.size}"
        },
        "margin-inline-end": {
          "$type": "spacing",
          "$value": "{nijmegen.space.inline.xs}"
        }
      },
      "color": {
        "$type": "color",
        "$value": "{nijmegen.color.donkerrood.100}"
      },
      "font-family": {
        "$type": "fontFamilies",
        "$value": "{utrecht.document.font-family}"
      },
      "font-size": {
        "$type": "fontSizes",
        "$value": "{utrecht.document.font-size}"
      },
      "font-weight": {
        "$type": "fontWeights",
        "$value": "{utrecht.document.font-weight}"
      },
      "line-height": {
        "$type": "lineHeights",
        "$value": "{utrecht.document.line-height}"
      }
    }
  }
}